simon_says/__init__.py
simon_says/ademco.py
simon_says/app.py
simon_says/client.py
simon_says/config.py
simon_says/control.py
simon_says/db.py
simon_says/events.py
simon_says/helpers.py
simon_says/log.py
simon_says/sensors.py
simon_says/version.py
simon_says-1.0.7.data/scripts/simon_event_handler
simon_says-1.0.7.dist-info/LICENSE
simon_says-1.0.7.dist-info/METADATA
simon_says-1.0.7.dist-info/WHEEL
simon_says-1.0.7.dist-info/top_level.txt
simon_says-1.0.7.dist-info/RECORD
